[{"file": "erfd.c", "line": 8, "func": "erf", "edges": [{"dest": 1, "total-usec": 62329.0, "total-count": 950, "usec": 65.60947368421053, "count": 1, "attrs": {"avg": 65.60947368421053, "var": 3382291.1938049844, "std": 1839.10064808998}}]}, {"file": "erfd.c", "line": 11, "func": "erf", "edges": [{"dest": 2, "total-usec": 30679.5, "total-count": 950, "usec": 32.29421052631579, "count": 1, "attrs": {"avg": 32.29421052631579, "var": 130.59844016620497, "std": 11.42796745559791}}]}, {"file": "erfd.c", "line": 24, "func": "erf", "edges": [{"dest": 3, "total-usec": 6929.0, "total-count": 950, "usec": 7.293684210526316, "count": 1, "attrs": {"avg": 7.293684210526316, "var": 6.800065373961209, "std": 2.60769349693579}}]}, {"file": "erfd.c", "line": 26, "func": "erf", "edges": [{"dest": 4, "total-usec": 9089.5, "total-count": 950, "usec": 9.567894736842105, "count": 1, "attrs": {"avg": 9.567894736842105, "var": 81.76723240997218, "std": 9.042523564247547}}]}, {"file": "erfd.c", "line": 28, "func": "erf", "edges": [{"dest": 5, "total-usec": 7309098.0, "total-count": 950, "usec": 7693.787368421053, "count": 1, "attrs": {"avg": 7693.787368421053, "var": 11402845.013208872, "std": 3376.8098870396702}}]}, {"file": "erfd.c", "line": 30, "func": "erf", "edges": []}]